buddybet_i18n/__init__.py
buddybet_i18n/i18n_service.py
buddybet_i18n-0.5.0.dist-info/METADATA
buddybet_i18n-0.5.0.dist-info/WHEEL
buddybet_i18n-0.5.0.dist-info/RECORD
