Metadata-Version: 2.3
Name: buddybet-i18n
Version: 0.5.0
Summary: Language internationalization library
Keywords: i18n,idioma
Author: ricardomarzochi07
Author-email: ricardomarzochi@gmail.com
Requires-Python: >=3.12
Classifier: Programming Language :: Python :: 3
Classifier: Programming Language :: Python :: 3.12
Classifier: Programming Language :: Python :: 3.13
Requires-Dist: i18n (>=0.2,<0.3)
